odoo10_addon_website_event_questions_template-10.0.1.0.0-py2.7-nspkg.pth
odoo/addons/website_event_questions_template/README.rst
odoo/addons/website_event_questions_template/__init__.py
odoo/addons/website_event_questions_template/__manifest__.py
odoo/addons/website_event_questions_template/i18n/es.po
odoo/addons/website_event_questions_template/models/__init__.py
odoo/addons/website_event_questions_template/models/event.py
odoo/addons/website_event_questions_template/models/event_question_template.py
odoo/addons/website_event_questions_template/security/ir.model.access.csv
odoo/addons/website_event_questions_template/static/description/icon.png
odoo/addons/website_event_questions_template/tests/__init__.py
odoo/addons/website_event_questions_template/tests/test_website_event_questions_template.py
odoo/addons/website_event_questions_template/views/event_view.xml
odoo/addons/website_event_questions_template/views/website_event_questions_template_view.xml
odoo10_addon_website_event_questions_template-10.0.1.0.0.dist-info/DESCRIPTION.rst
odoo10_addon_website_event_questions_template-10.0.1.0.0.dist-info/METADATA
odoo10_addon_website_event_questions_template-10.0.1.0.0.dist-info/RECORD
odoo10_addon_website_event_questions_template-10.0.1.0.0.dist-info/WHEEL
odoo10_addon_website_event_questions_template-10.0.1.0.0.dist-info/metadata.json
odoo10_addon_website_event_questions_template-10.0.1.0.0.dist-info/namespace_packages.txt
odoo10_addon_website_event_questions_template-10.0.1.0.0.dist-info/top_level.txt
